{"version":"v1.0 b1","name":"showcase3","creator":"Player602","mapInfo":{"x":5,"y":6,"z":8,"blockList":[{"key":"wool","value":8},{"key":"wool","value":8},{"key":"wool","value":8},{"key":"wool","value":8},{"key":"wool","value":8},{"key":"wool","value":8},{"key":"wool","value":8},{"key":"wool","value":8},{"key":"wool","value":7},{"key":"air","value":0},{"key":"air","value":0},{"key":"air","value":0},{"key":"air","value":0},{"key":"air","value":0},{"key":"air","value":0},{"key":"air","value":0},{"key":"wool","value":7},{"key":"air","value":0},{"key":"air","value":0},{"key":"air","value":0},{"key":"air","value":0},{"key":"air","value":0},{"key":"air","value":0},{"key":"air","value":0},{"key":"wool","value":7},{"key":"air","value":0},{"key":"air","value":0},{"key":"air","value":0},{"key":"air","value":0},{"key":"air","value":0},{"key":"air","value":0},{"key":"air","value":0},{"key":"wool","value":7},{"key":"air","value":0},{"key":"air","value":0},{"key":"air","value":0},{"key":"air","value":0},{"key":"air","value":0},{"key":"air","value":0},{"key":"air","value":0},{"key":"wool","value":7},{"key":"air","value":0},{"key":"air","value":0},{"key":"air","value":0},{"key":"air","value":0},{"key":"air","value":0},{"key":"air","value":0},{"key":"air","value":0},{"key":"wool","value":8},{"key":"wool","value":8},{"key":"wool","value":8},{"key":"wool","value":8},{"key":"wool","value":8},{"key":"wool","value":8},{"key":"wool","value":8},{"key":"wool","value":8},{"key":"wool","value":7},{"key":"air","value":0},{"key":"air","value":0},{"key":"air","value":0},{"key":"air","value":0},{"key":"air","value":0},{"key":"air","value":0},{"key":"air","value":0},{"key":"wool","value":7},{"key":"air","value":0},{"key":"air","value":0},{"key":"air","value":0},{"key":"air","value":0},{"key":"air","value":0},{"key":"air","value":0},{"key":"air","value":0},{"key":"wool","value":7},{"key":"air","value":0},{"key":"air","value":0},{"key":"air","value":0},{"key":"air","value":0},{"key":"air","value":0},{"key":"air","value":0},{"key":"air","value":0},{"key":"wool","value":7},{"key":"air","value":0},{"key":"air","value":0},{"key":"air","value":0},{"key":"air","value":0},{"key":"air","value":0},{"key":"air","value":0},{"key":"air","value":0},{"key":"wool","value":7},{"key":"air","value":0},{"key":"air","value":0},{"key":"air","value":0},{"key":"air","value":0},{"key":"air","value":0},{"key":"air","value":0},{"key":"air","value":0},{"key":"wool","value":8},{"key":"wool","value":8},{"key":"wool","value":8},{"key":"wool","value":8},{"key":"wool","value":8},{"key":"wool","value":8},{"key":"wool","value":8},{"key":"wool","value":8},{"key":"wool","value":7},{"key":"air","value":0},{"key":"air","value":0},{"key":"air","value":0},{"key":"air","value":0},{"key":"air","value":0},{"key":"air","value":0},{"key":"air","value":0},{"key":"wool","value":7},{"key":"air","value":0},{"key":"air","value":0},{"key":"air","value":0},{"key":"air","value":0},{"key":"air","value":0},{"key":"air","value":0},{"key":"air","value":0},{"key":"wool","value":7},{"key":"air","value":0},{"key":"air","value":0},{"key":"air","value":0},{"key":"air","value":0},{"key":"air","value":0},{"key":"air","value":0},{"key":"air","value":0},{"key":"wool","value":7},{"key":"air","value":0},{"key":"air","value":0},{"key":"air","value":0},{"key":"air","value":0},{"key":"air","value":0},{"key":"air","value":0},{"key":"air","value":0},{"key":"wool","value":7},{"key":"air","value":0},{"key":"air","value":0},{"key":"air","value":0},{"key":"air","value":0},{"key":"air","value":0},{"key":"air","value":0},{"key":"air","value":0},{"key":"wool","value":8},{"key":"wool","value":8},{"key":"wool","value":8},{"key":"wool","value":8},{"key":"wool","value":8},{"key":"wool","value":8},{"key":"wool","value":8},{"key":"wool","value":8},{"key":"wool","value":7},{"key":"air","value":0},{"key":"air","value":0},{"key":"air","value":0},{"key":"air","value":0},{"key":"air","value":0},{"key":"air","value":0},{"key":"air","value":0},{"key":"wool","value":7},{"key":"air","value":0},{"key":"air","value":0},{"key":"air","value":0},{"key":"air","value":0},{"key":"air","value":0},{"key":"air","value":0},{"key":"air","value":0},{"key":"wool","value":7},{"key":"air","value":0},{"key":"air","value":0},{"key":"air","value":0},{"key":"air","value":0},{"key":"air","value":0},{"key":"air","value":0},{"key":"air","value":0},{"key":"wool","value":7},{"key":"air","value":0},{"key":"air","value":0},{"key":"air","value":0},{"key":"air","value":0},{"key":"air","value":0},{"key":"air","value":0},{"key":"air","value":0},{"key":"wool","value":7},{"key":"air","value":0},{"key":"air","value":0},{"key":"air","value":0},{"key":"air","value":0},{"key":"air","value":0},{"key":"air","value":0},{"key":"air","value":0},{"key":"wool","value":8},{"key":"wool","value":8},{"key":"wool","value":8},{"key":"wool","value":8},{"key":"wool","value":8},{"key":"wool","value":8},{"key":"wool","value":8},{"key":"wool","value":8},{"key":"wool","value":7},{"key":"air","value":0},{"key":"air","value":0},{"key":"air","value":0},{"key":"air","value":0},{"key":"air","value":0},{"key":"air","value":0},{"key":"air","value":0},{"key":"wool","value":7},{"key":"air","value":0},{"key":"air","value":0},{"key":"air","value":0},{"key":"air","value":0},{"key":"air","value":0},{"key":"air","value":0},{"key":"air","value":0},{"key":"wool","value":7},{"key":"air","value":0},{"key":"air","value":0},{"key":"air","value":0},{"key":"air","value":0},{"key":"air","value":0},{"key":"air","value":0},{"key":"air","value":0},{"key":"wool","value":7},{"key":"air","value":0},{"key":"air","value":0},{"key":"air","value":0},{"key":"air","value":0},{"key":"air","value":0},{"key":"air","value":0},{"key":"air","value":0},{"key":"wool","value":7},{"key":"air","value":0},{"key":"air","value":0},{"key":"air","value":0},{"key":"air","value":0},{"key":"air","value":0},{"key":"air","value":0},{"key":"air","value":0}]},"botInfo":{"botCode":"package caterpillow.trainer.bots.testing;\n\nimport caterpillow.AimTrainer;\nimport caterpillow.trainer.bots.BotInfo;\nimport caterpillow.trainer.bots.BotReflectionCrap;\nimport caterpillow.trainer.scenarios.ScenarioPlayer;\nimport caterpillow.trainer.util.PositionUtils;\nimport net.minecraft.block.state.IBlockState;\nimport net.minecraft.client.Minecraft;\nimport net.minecraft.util.BlockPos;\nimport net.minecraft.util.Vec3;\n\nimport java.util.ArrayList;\nimport java.util.Random;\n\npublic class Tile {\n\n    private ScenarioPlayer scenarioPlayer;\n\n    public int botNumber;\n\n    public ArrayList\u003cBlockPos\u003e getSpawnpoints() {\n        return spawnpoints;\n    }\n\n    public ArrayList\u003cBlockPos\u003e spawnpoints;\n    public ArrayList\u003cBlockPos\u003e availableSpawns;\n    public Vec3 position;\n    private BotInfo botInfo;\n    private BotReflectionCrap botReflectionCrap;\n    Random generator;\n    IBlockState iBlockState;\n\n    public Tile(ScenarioPlayer scenarioPlayer, caterpillow.trainer.bots.BotReflectionCrap botReflectionCrap, int botNumber) {\n        this.scenarioPlayer \u003d scenarioPlayer;\n        this.botNumber \u003d botNumber;\n        this.botReflectionCrap \u003d botReflectionCrap;\n    }\n\n    public void start() {\n        generator \u003d new Random();\n        System.out.println(\"omg guys it started\");\n        spawn();\n    }\n\n    public void onHit(Vec3 hitVec) {\n        spawn();\n    }\n\n    public void onTick() {\n\n    }\n\n    public void onWorldRender(float partialTicks) {\n\n    }\n\n    public void spawn() {\n        this.availableSpawns \u003d new ArrayList\u003c\u003e(spawnpoints);\n        for (BlockPos pos : scenarioPlayer.takenBlocks) {\n            availableSpawns.removeIf(blockPos -\u003e PositionUtils.isPosEqual(blockPos, pos));\n        }\n        // grabs a random available spawnspot\n        int index \u003d generator.nextInt(availableSpawns.size());\n        BlockPos newPos \u003d availableSpawns.get(index);\n\n        // sets the old block to its original form\n        if (position !\u003d null)\n            Minecraft.getMinecraft().getIntegratedServer().getEntityWorld().setBlockState(new BlockPos(position), iBlockState);\n\n        // saves the new spot\u0027s original block\n        iBlockState \u003d Minecraft.getMinecraft().getIntegratedServer().getEntityWorld().getBlockState(newPos);\n\n        // updates scenarioplayer\u0027s taken blocks\n        if (position !\u003d null)\n            scenarioPlayer.updateTakenBlocks(new BlockPos(position), newPos);\n        else\n            scenarioPlayer.updateTakenBlocks(null, newPos);\n\n        // sets the new block to the target\n        Minecraft.getMinecraft().getIntegratedServer().getEntityWorld().setBlockState(newPos, AimTrainer.instance.settingsManager.getTargetBlockState());\n\n\n\n        // sets the position field to the new position\n        position \u003d new Vec3(newPos.getX(), newPos.getY(), newPos.getZ());\n    }\n\n    public void setReflectionObject(BotReflectionCrap botReflectionCrap) {\n        this.botReflectionCrap \u003d botReflectionCrap;\n    }\n\n}\n","botCount":3,"spawnRegions":[{"key":{"x":0,"y":1,"z":0},"value":{"x":4,"y":5,"z":0}}]}}