{"stat.useItem.minecraft.wooden_door":3,"stat.flyOneCm":50470,"stat.useItem.minecraft.glass":60,"stat.walkOneCm":26231,"stat.drop":1,"stat.jump":160,"stat.trappedChestTriggered":2,"stat.playOneMinute":12782,"achievement.openInventory":1,"stat.useItem.minecraft.planks":5,"stat.leaveGame":1,"stat.useItem.minecraft.trapped_chest":1,"stat.crouchOneCm":789,"stat.timeSinceDeath":12782,"stat.useItem.minecraft.dirt":210,"stat.sprintOneCm":4705,"achievement.exploreAllBiomes":{"value":0,"progress":["ForestHills","Forest"]}}